MANIFEST.in
README.md
README.rst
setup.py
agung96tm_funniest/__init__.py
agung96tm_funniest/command_line.py
agung96tm_funniest/text.py
agung96tm_funniest.egg-info/PKG-INFO
agung96tm_funniest.egg-info/SOURCES.txt
agung96tm_funniest.egg-info/dependency_links.txt
agung96tm_funniest.egg-info/entry_points.txt
agung96tm_funniest.egg-info/not-zip-safe
agung96tm_funniest.egg-info/requires.txt
agung96tm_funniest.egg-info/top_level.txt
bin/funniest-joke