Metadata-Version: 1.1
Name: agung96tm-funniest
Version: 0.1.8.2
Summary: The agung96tm_funniest jokes
Home-page: http://localhost:8000
Author: king
Author-email: king@example.com
License: MIT
Keywords: funniest joke comedy flying circus
Platform: UNKNOWN
Classifier: Development Status :: 3 - Alpha
Classifier: Programming Language :: Python :: 2.7
Classifier: Topic :: Text Processing :: Linguistic
